Metadata-Version: 2.1
Name: socpipe
Version: 0.0.6
Summary: very simple way of inter-process communication
Home-page: https://github.com/kana-lab/socpipe/
Maintainer: R. Nakano
Maintainer-email: yukiakari@ichigo.me
License: UNKNOWN
Keywords: inter-process,multi process,communication,マルチプロセス,プロセス間通信,rpc
Platform: UNKNOWN
Classifier: Programming Language :: Python :: 3
Classifier: License :: OSI Approved :: MIT License
Classifier: Operating System :: OS Independent
Classifier: Intended Audience :: Developers
Requires-Python: >=3.6, <4
